README.md
codepost_stats/__init__.py
codepost_stats/analyzers/__init__.py
codepost_stats/analyzers/abstract/__init__.py
codepost_stats/analyzers/abstract/base.py
codepost_stats/analyzers/abstract/simple.py
codepost_stats/analyzers/pool.py
codepost_stats/analyzers/standard.py
codepost_stats/event_loop.py
codepost_stats/helpers.py
codepost_stats-0.1.4.dist-info/LICENSE
codepost_stats-0.1.4.dist-info/WHEEL
codepost_stats-0.1.4.dist-info/METADATA
codepost_stats-0.1.4.dist-info/RECORD
