Metadata-Version: 2.1
Name: codepost-stats
Version: 0.1.4
Summary: A system to compile statistics automatically from a course on the codePost platform.
Home-page: https://github.com/jlumbroso/codepost-stats
License: LGPL-3.0-or-later
Keywords: codePost
Author: Jérémie Lumbroso
Author-email: lumbroso@cs.princeton.edu
Requires-Python: >=3.8,<4.0
Classifier: Development Status :: 3 - Alpha
Classifier: License :: OSI Approved :: GNU Lesser General Public License v3 or later (LGPLv3+)
Classifier: Programming Language :: Python :: 3
Classifier: Programming Language :: Python :: 3.10
Classifier: Programming Language :: Python :: 3.8
Classifier: Programming Language :: Python :: 3.9
Classifier: Topic :: Software Development :: Libraries :: Python Modules
Requires-Dist: codepost (>=0.2.25,<0.3.0)
Requires-Dist: tqdm (>=4.48.2,<5.0.0)
Project-URL: Repository, https://github.com/jlumbroso/codepost-stats
